{
  "datas": {
    "alias": 0,
    "atk": 1700,
    "attribute": 32,
    "category": 1074003968,
    "def": 2400,
    "id": 101305086,
    "level": 3,
    "ot": 2,
    "race": 1,
    "setcode": 0,
    "type": 8388641
  },
  "id": 101305086,
  "name": "Shamanite Shamancavaleiro",
  "texts": {
    "desc": "2+ monstros de Nível 3\r\nSe este card for Invocado por Invocação-Xyz ou se uma Armadilha que você controla é banida: você pode escolher 1 das suas Armadilhas banidas; associe-a neste card.\r\nVocê pode desassociar qualquer número de matérias deste card, então escolha 1 monstro de TREVAS no seu Cemitério ou banimento com um Nível igual ao número desassociado; Invoque-o por Invocação-Especial.\r\nVocê só pode usar cada um dos efeitos de \"Shamanite Shamancavaleiro\" uma vez por turno.",
    "id": 101305086,
    "name": "Shamanite Shamancavaleiro",
    "str1": "Associar Matéria Xyz",
    "str10": "",
    "str11": "",
    "str12": "",
    "str13": "",
    "str14": "",
    "str15": "",
    "str16": "",
    "str2": "Invocação Especial",
    "str3": "Escolha a quantidade de Matérias Xyz a desassociar",
    "str4": "",
    "str5": "",
    "str6": "",
    "str7": "",
    "str8": "",
    "str9": ""
  }
}
