{
  "datas": {
    "alias": 0,
    "atk": 0,
    "attribute": 0,
    "category": 528,
    "def": 0,
    "id": 101305062,
    "level": 0,
    "ot": 1,
    "race": 0,
    "setcode": 0,
    "type": 2
  },
  "id": 101305062,
  "name": "Registri Rituali Corrotti",
  "texts": {
    "desc": "Rivela 1 Magia Rituale dalla tua mano o Deck, e aggiungi 1 mostro che la menziona dal tuo Deck alla tua mano.\r\nSe un Mostro Rituale scoperto che controlli lascia il Terreno per effetto di una carta mentre questa carta è nel tuo Cimitero, e non controlli Mostri non-Rituale scoperti: puoi aggiungere questa carta alla tua mano.\r\nPuoi utilizzare ogni effetto di \"Registri Rituali Corrotti\" una sola volta per turno.",
    "id": 101305062,
    "name": "Registri Rituali Corrotti",
    "str1": "Effetto di aggiunta alla mano",
    "str10": "",
    "str11": "",
    "str12": "",
    "str13": "",
    "str14": "",
    "str15": "",
    "str16": "",
    "str2": "Rimettere in mano",
    "str3": "",
    "str4": "",
    "str5": "",
    "str6": "",
    "str7": "",
    "str8": "",
    "str9": ""
  }
}
