{
  "datas": {
    "alias": 0,
    "atk": 300,
    "attribute": 32,
    "category": 262656,
    "def": 130,
    "id": 101305039,
    "level": 2,
    "ot": 1,
    "race": 4,
    "setcode": 462,
    "type": 67108897
  },
  "id": 101305039,
  "name": "Inviato del Patrono Potente delle Preghiere Pure",
  "texts": {
    "desc": "2 mostri non-Link\r\nSe questa carta è Evocata Link e hai un mostro \"Patrono Potente\" nel tuo Cimitero: puoi aggiungere 1 carta \"Teorealizzare\" dal tuo Deck alla tua mano.\r\nDurante la Main Phase, se controlli un altro mostro Fata OSCURITÀ, puoi (Effetto Rapido): immediatamente dopo che questo effetto si è risolto, Evoca Link utilizzando materiali che controlli, inclusa questa carta.\r\nPuoi utilizzare ogni effetto di \"Inviato del Patrono Potente delle Preghiere Pure\" una sola volta per turno.",
    "id": 101305039,
    "name": "Inviato del Patrono Potente delle Preghiere Pure",
    "str1": "Aggiungere alla mano",
    "str10": "",
    "str11": "",
    "str12": "",
    "str13": "",
    "str14": "",
    "str15": "",
    "str16": "",
    "str2": "Evocazione Link",
    "str3": "",
    "str4": "",
    "str5": "",
    "str6": "",
    "str7": "",
    "str8": "",
    "str9": ""
  }
}
