{
  "datas": {
    "alias": 0,
    "atk": 1200,
    "attribute": 16,
    "category": 262659,
    "def": 1000,
    "id": 101305026,
    "level": 4,
    "ot": 1,
    "race": 32,
    "setcode": 0,
    "type": 33
  },
  "id": 101305026,
  "name": "Caccia Grigio Stratificato",
  "texts": {
    "desc": "Puoi offrire come Tributo questa carta e rivelare 1 mostro Macchina nella tua mano; aggiungi alla tua mano 1 mostro Macchina dal tuo Deck con un Attributo diverso da quello del mostro rivelato, poi, se hai aggiunto un mostro con 1200 o meno ATK, puoi Evocare Specialmente 1 mostro Macchina dalla tua mano.\r\nSe uno o più mostri in tuo possesso vengono distrutti dall'effetto di una carta, mentre questa carta è nel tuo Cimitero: puoi bandire questa carta; distruggi 1 carta sul Terreno.\r\nPuoi utilizzare ciascun effetto di \"Caccia Grigio Stratificato\" una sola volta per turno.",
    "id": 101305026,
    "name": "Caccia Grigio Stratificato",
    "str1": "Effetto di aggiunta alla mano",
    "str10": "",
    "str11": "",
    "str12": "",
    "str13": "",
    "str14": "",
    "str15": "",
    "str16": "",
    "str2": "Effetto di distruzione",
    "str3": "Evocazione Speciale?",
    "str4": "",
    "str5": "",
    "str6": "",
    "str7": "",
    "str8": "",
    "str9": ""
  }
}
