{
  "datas": {
    "alias": 0,
    "atk": 1700,
    "attribute": 32,
    "category": 1074003968,
    "def": 2400,
    "id": 101305086,
    "level": 3,
    "ot": 2,
    "race": 1,
    "setcode": 0,
    "type": 8388641
  },
  "id": 101305086,
  "name": "Shamanite Shamanknight",
  "texts": {
    "desc": "2+ Level 3 monsters\nIf this card is Xyz Summoned, or if a Trap you own is banished: You can target 1 of your banished Traps; attach it to this card. You can detach any number of materials from this card, then target 1 DARK monster in your GY or banishment with a Level equal to the number detached; Special Summon it. You can only use each effect of \"Shamanite Shamanknight\" once per turn.",
    "id": 101305086,
    "name": "Shamanite Shamanknight",
    "str1": "Attach Xyz material",
    "str10": "",
    "str11": "",
    "str12": "",
    "str13": "",
    "str14": "",
    "str15": "",
    "str16": "",
    "str2": "Special Summon",
    "str3": "Select the number of Xyz Materials to detach",
    "str4": "",
    "str5": "",
    "str6": "",
    "str7": "",
    "str8": "",
    "str9": ""
  }
}
