{
  "datas": {
    "alias": 0,
    "atk": 0,
    "attribute": 0,
    "category": 528,
    "def": 0,
    "id": 101305062,
    "level": 0,
    "ot": 1,
    "race": 0,
    "setcode": 0,
    "type": 2
  },
  "id": 101305062,
  "name": "Anales de Ritual Corruptos",
  "texts": {
    "desc": "Revela 1 Mágica de Ritual en tu mano o Deck y añade a tu mano 1 monstruo que la mencione desde tu Deck. \r\nSi uno o más Monstruos de Ritual boca arriba que controles dejan el Campo por efecto de carta mientras esta carta está en tu Cementerio, y ahora no controlas monstruos que no sean de Ritual boca arriba: puedes añadir esta carta a tu mano. \r\nSólo puedes usar cada uno de los efectos de \"Anales de Ritual Corruptos\" una vez por turno.",
    "id": 101305062,
    "name": "Anales de Ritual Corruptos",
    "str1": "Añadir a tu mano desde tu Deck 1 monstruo que mencione la Mágica Ritual revelada",
    "str10": "",
    "str11": "",
    "str12": "",
    "str13": "",
    "str14": "",
    "str15": "",
    "str16": "",
    "str2": "Añadir esta carta en tu Cementerio a tu mano",
    "str3": "",
    "str4": "",
    "str5": "",
    "str6": "",
    "str7": "",
    "str8": "",
    "str9": ""
  }
}
