{
  "datas": {
    "alias": 0,
    "atk": 4500,
    "attribute": 16,
    "category": 131092,
    "def": 3800,
    "id": 100261005,
    "level": 12,
    "ot": 1,
    "race": 8192,
    "setcode": 6422749,
    "type": 4194401
  },
  "id": 100261005,
  "name": "ブルーアイズ・トゥーン・アルティメットドラゴン",
  "texts": {
    "desc": "「ブルーアイズ・トゥーン・ドラゴン」＋トゥーンモンスター×２\t\r\n自分の手札・フィールド・墓地の上記のカードをデッキ・ＥＸデッキに戻した場合のみ特殊召喚できる。\r\n①：自分のトゥーンモンスターは直接攻撃できる。\r\n②：１ターンに１度、自分メインフェイズに発動できる。\r\n「トゥーン」カードまたはそのカード名が記されたカード１枚を自分の墓地から手札に加える。\r\n③：自分のトゥーンモンスターが攻撃されるダメージ計算時に発動できる。\r\nそのモンスターをダメージステップ終了時まで除外する。",
    "id": 100261005,
    "name": "ブルーアイズ・トゥーン・アルティメットドラゴン",
    "str1": "",
    "str10": "",
    "str11": "",
    "str12": "",
    "str13": "",
    "str14": "",
    "str15": "",
    "str16": "",
    "str2": "回収",
    "str3": "除外",
    "str4": "",
    "str5": "",
    "str6": "",
    "str7": "",
    "str8": "",
    "str9": ""
  }
}
