{
  "datas": {
    "alias": 0,
    "atk": 0,
    "attribute": 0,
    "category": 262144,
    "def": 0,
    "id": 100200291,
    "level": 0,
    "ot": 1,
    "race": 0,
    "setcode": 0,
    "type": 524290
  },
  "id": 100200291,
  "name": "Capsule Monster Chess",
  "texts": {
    "desc": "ในช่วง Main Phase: ผู้เล่นที่เป็นเจ้าของเทิร์นสามารถเลือกเป้าหมายมอนสเตอร์ 1 ใบในสุสานของตน แล้วนำมอนสเตอร์ใบนั้นวางหงายหน้าในโซนเวทมนตร์และกับดักของตนในฐานะ Continuous Spell ในช่วง End Phase: ผู้เล่นที่เป็นเจ้าของเทิร์นสามารถส่ง Monster Card หงายหน้า 1 ใบที่ตนควบคุมไปยังสุสาน จากนั้นทำการ Special Summon มอนสเตอร์ 1 ใบจากเด็คที่มีประเภทและคุณสมบัติเดิมเหมือนกัน แต่มีเลเวลต้นฉบับสูงกว่า 1, 2 หรือ 3 เลเวล คุณสามารถใช้งานเอฟเฟกต์แต่ละอย่างของ \"Capsule Monster Chess\" ได้เทิร์นละ 1 ครั้งเท่านั้น",
    "id": 100200291,
    "name": "Capsule Monster Chess",
    "str1": "",
    "str10": "",
    "str11": "",
    "str12": "",
    "str13": "",
    "str14": "",
    "str15": "",
    "str16": "",
    "str2": "วางมอนสเตอร์",
    "str3": "เรียกพิเศษ",
    "str4": "",
    "str5": "",
    "str6": "",
    "str7": "",
    "str8": "",
    "str9": ""
  }
}
