{
  "datas": {
    "alias": 0,
    "atk": 2400,
    "attribute": 8,
    "category": 0,
    "def": 1500,
    "id": 101306011,
    "level": 7,
    "ot": 1,
    "race": 2,
    "setcode": 740,
    "type": 33
  },
  "id": 101306011,
  "name": "Yoa the Plague Deity Ashtra",
  "texts": {
    "desc": "คุณสามารถ Special Summon การ์ดใบนี้ (จากบนมือของคุณ) โดยการเปิดเผยการ์ดที่คว่ำหน้าอยู่ 1 ใบที่คุณควบคุมอยู่แล้วนำการ์ดใบนั้นกลับขึ้นมือ/Extra Deck คุณสามารถ Special Summon \"Yoa the Plague Deity Ashtra\" ได้เพียงเทิร์นละ 1 ครั้งด้วยวิธีนี้ คุณสามารถใช้งานเอฟเฟกต์แต่ละอย่างของ \"Yoa the Plague Deity Ashtra\" ได้เพียงเทิร์นละ 1 ครั้งเท่านั้น ในช่วง Main Phase ของคุณ: คุณสามารถ Set การ์ด \"Ashtra\" เวทมนตร์/กับดักจากใน Deck ของคุณ 1 ใบ ในช่วงเทิร์นของฝ่ายตรงข้าม (Quick Effect): คุณสามารถเลือกเป้าหมายมอนสเตอร์ที่หงายหน้าอยู่บนสนาม 1 ใบ; เพิ่มหรือลดเลเวลของมอนสเตอร์ใบนั้นลง 1",
    "id": 101306011,
    "name": "Yoa the Plague Deity Ashtra",
    "str1": "",
    "str10": "",
    "str11": "",
    "str12": "",
    "str13": "",
    "str14": "",
    "str15": "",
    "str16": "",
    "str2": "หมอบ",
    "str3": "เปลี่ยนระดับ",
    "str4": "เพิ่มระดับ",
    "str5": "ลดระดับ",
    "str6": "",
    "str7": "",
    "str8": "",
    "str9": ""
  }
}
